banking_logging/__init__.py
banking_logging/banking_logging.py
banking_logging-0.2.3.dist-info/METADATA
banking_logging-0.2.3.dist-info/WHEEL
banking_logging-0.2.3.dist-info/top_level.txt
banking_logging-0.2.3.dist-info/RECORD
