Metadata-Version: 2.1
Name: banking-logging
Version: 0.2.3
Summary: Shared loggers for banking_api project
Home-page: 
Download-URL: 
Maintainer: Edward Azizov
Maintainer-email: edazizovv@gmail.com
License: Proprietary
Requires-Python: >=3.10
